{
  "username": "JohnDoe",
  "data": [
    {
      "ID": "J1",
      "NAME": "default",
      "TABLES": [
        {
          "ID": "T3",
          "NAME": "HLT"
        },
        {
          "ID": "T4",
          "NAME": "KBW"
        },
        {
          "ID": "T1",
          "NAME": "LBF"
        }
      ]
    },
    {
      "ID": "J2",
      "NAME": "default (2)",
      "TABLES": [
        {
          "ID": "T3",
          "NAME": "HLT"
        },
        {
          "ID": "T4",
          "NAME": "KBW"
        }
      ]
    },
    {
      "ID": "J3",
      "NAME": "default (3)",
      "TABLES": [
        {
          "ID": "T1",
          "NAME": "LBF"
        }
      ]
    },
    {
      "ID": "J4",
      "NAME": "default (4)",
      "TABLES": [
      ]
    },
    {
      "ID": "J5",
      "NAME": "default (5)",
      "TABLES": [
      ]
    }
  ]
}